{
  "version": 2,
  "extractor": "papercropper",
  "figures": [
    {
      "url": "assets/figures/arxiv/2607.01721v1/fig-001.webp",
      "caption": "",
      "page": 0,
      "index": 1,
      "width": 1398,
      "height": 981,
      "label": "Figure"
    },
    {
      "url": "assets/figures/arxiv/2607.01721v1/fig-002.webp",
      "caption": "",
      "page": 0,
      "index": 2,
      "width": 861,
      "height": 259,
      "label": "Figure"
    },
    {
      "url": "assets/figures/arxiv/2607.01721v1/fig-003.webp",
      "caption": "",
      "page": 0,
      "index": 3,
      "width": 1770,
      "height": 722,
      "label": "Figure"
    },
    {
      "url": "assets/figures/arxiv/2607.01721v1/fig-004.webp",
      "caption": "",
      "page": 0,
      "index": 4,
      "width": 851,
      "height": 473,
      "label": "Figure"
    },
    {
      "url": "assets/figures/arxiv/2607.01721v1/fig-005.webp",
      "caption": "",
      "page": 0,
      "index": 5,
      "width": 852,
      "height": 449,
      "label": "Figure"
    },
    {
      "url": "assets/figures/arxiv/2607.01721v1/fig-006.webp",
      "caption": "",
      "page": 0,
      "index": 6,
      "width": 856,
      "height": 384,
      "label": "Figure"
    },
    {
      "url": "assets/figures/arxiv/2607.01721v1/fig-007.webp",
      "caption": "",
      "page": 0,
      "index": 7,
      "width": 1379,
      "height": 665,
      "label": "Figure"
    },
    {
      "url": "assets/figures/arxiv/2607.01721v1/fig-008.webp",
      "caption": "",
      "page": 0,
      "index": 8,
      "width": 1630,
      "height": 1093,
      "label": "Figure"
    },
    {
      "url": "assets/figures/arxiv/2607.01721v1/fig-009.webp",
      "caption": "",
      "page": 0,
      "index": 9,
      "width": 730,
      "height": 430,
      "label": "Figure"
    },
    {
      "url": "assets/figures/arxiv/2607.01721v1/fig-010.webp",
      "caption": "",
      "page": 0,
      "index": 10,
      "width": 1376,
      "height": 669,
      "label": "Figure"
    },
    {
      "url": "assets/figures/arxiv/2607.01721v1/fig-011.webp",
      "caption": "",
      "page": 0,
      "index": 11,
      "width": 1375,
      "height": 669,
      "label": "Figure"
    },
    {
      "url": "assets/figures/arxiv/2607.01721v1/fig-012.webp",
      "caption": "",
      "page": 0,
      "index": 12,
      "width": 1051,
      "height": 692,
      "label": "Figure"
    },
    {
      "url": "assets/figures/arxiv/2607.01721v1/fig-013.webp",
      "caption": "",
      "page": 0,
      "index": 13,
      "width": 1721,
      "height": 1792,
      "label": "Figure"
    }
  ]
}